MANIFEST.in
README.md
setup.py
bin/CreateHydroShareResource.py
bin/DumpClimateStationInfo.py
bin/DumpMetadataToiRODSXML.py
bin/GenerateSoilPropertyRastersFromSOLIM.py
bin/GenerateSoilPropertyRastersFromSSURGO.py
bin/GetBoundingboxFromStudyareaShapefile.py
bin/GetCatchmentShapefileForHYDRO1kBasins.py
bin/GetCatchmentShapefileForNHDStreamflowGage.py
bin/GetDEMExplorerDEMForBoundingbox.py
bin/GetGADEMForBoundingBox.py
bin/GetGHCNDailyClimateDataForBoundingboxCentroid.py
bin/GetGHCNDailyClimateDataForStationsInBoundingbox.py
bin/GetHYDRO1kDEMForBoundingbox.py
bin/GetNHDStreamflowGageIdentifiersAndLocation.py
bin/GetNLCDForDEMExtent.py
bin/GetSSURGOFeaturesForBoundingbox.py
bin/GetSoilGridAustralia.py
bin/GetUSGSDEMForBoundingbox.py
bin/GetUSGSNLCDForDEMExtent.py
bin/RegisterDEM.py
bin/RegisterGage.py
bin/RegisterRaster.py
bin/RegisterStudyAreaShapefile.py
bin/RunCmd.py
bin/GHCNDSetup/GHCNDSetup.py
bin/NHDPlusV2Setup/NHDPlusV2Setup.py
cgi/GetCatchmentFeaturesForStreamflowGage
cgi/LocateStreamflowGage
ecohydrolib/__init__.py
ecohydrolib/context.py
ecohydrolib/dbf.py
ecohydrolib/grasslib.py
ecohydrolib/hydroshare.py
ecohydrolib/metadata.py
ecohydrolib/util.py
ecohydrolib/wcslib.py
ecohydrolib.egg-info/PKG-INFO
ecohydrolib.egg-info/SOURCES.txt
ecohydrolib.egg-info/dependency_links.txt
ecohydrolib.egg-info/not-zip-safe
ecohydrolib.egg-info/requires.txt
ecohydrolib.egg-info/top_level.txt
ecohydrolib/climatedata/__init__.py
ecohydrolib/climatedata/ghcndquery.py
ecohydrolib/command/__init__.py
ecohydrolib/command/base.py
ecohydrolib/command/dem.py
ecohydrolib/command/exceptions.py
ecohydrolib/command/hydroshare.py
ecohydrolib/command/landcover.py
ecohydrolib/command/soil.py
ecohydrolib/geosciaus/__init__.py
ecohydrolib/geosciaus/demwcs.py
ecohydrolib/geosciaus/soilwcs.py
ecohydrolib/hydro1k/__init__.py
ecohydrolib/hydro1k/basins.py
ecohydrolib/hydro1k/demtile.py
ecohydrolib/nhdplus2/__init__.py
ecohydrolib/nhdplus2/networkanalysis.py
ecohydrolib/nhdplus2/webservice.py
ecohydrolib/nlcd/__init__.py
ecohydrolib/nlcd/daacquery.py
ecohydrolib/solim/__init__.py
ecohydrolib/solim/inference.py
ecohydrolib/spatialdata/__init__.py
ecohydrolib/spatialdata/utils.py
